Metadata-Version: 1.1
Name: dbug
Version: 1.0b5
Summary: Print tools for debuging
Home-page: http://leo-flaventin.com
Author: Léo Flaventin Hauchecorne
Author-email: hl037.prog@gmail.com
License: Public Domain
Project-URL: Documentation, https://github.com/hl037/dbug.py/blob/master/dbug/__init__.py
Project-URL: Source, https://github.com/hl037/dbug.py
Project-URL: Tracker, https://github.com/hl037/dbug.py/issues
Platform: UNKNOWN
Classifier: Development Status :: 4 - Beta
Classifier: Intended Audience :: Developers
Classifier: License :: Public Domain
Classifier: Programming Language :: Python
Classifier: Programming Language :: Python :: 2
Classifier: Programming Language :: Python :: 3
Classifier: Topic :: Software Development :: Debuggers
